hotbit/__init__.py
hotbit/auth.py
hotbit/officialApi.py
hotbit/reverseApi.py
hotbit-0.1.1.dist-info/LICENSE
hotbit-0.1.1.dist-info/METADATA
hotbit-0.1.1.dist-info/WHEEL
hotbit-0.1.1.dist-info/top_level.txt
hotbit-0.1.1.dist-info/RECORD
