Metadata-Version: 2.1
Name: hotbit
Version: 0.1.1
Summary: A Python package for the cryptocurrency exchange Hotbit that doesn't require an API Key, making it available to everyone
Home-page: https://github.com/jona799t/python-hotbit
Author: jona799t
License: UNKNOWN
Keywords: hotbit,api,crypto,exchange
Platform: UNKNOWN
Classifier: Development Status :: 1 - Planning
Classifier: Intended Audience :: Developers
Classifier: Programming Language :: Python :: 3
Classifier: Operating System :: Unix
Classifier: Operating System :: MacOS :: MacOS X
Classifier: Operating System :: Microsoft :: Windows
Requires-Dist: 2captcha-python
Requires-Dist: anticaptchaofficial
Requires-Dist: pycryptodome
Requires-Dist: requests
Requires-Dist: requestsWS
Requires-Dist: twocaptcha
Requires-Dist: undetected-chromedriver
